ezsam-0.5.0.dist-info/METADATA
ezsam-0.5.0.dist-info/WHEEL
ezsam-0.5.0.dist-info/entry_points.txt
ezsam-0.5.0.dist-info/licenses/LICENSE
ezsam/__init__.py
ezsam/cli/__init__.py
ezsam/cli/app.py
ezsam/cli/config/defaults.py
ezsam/cli/config/utils.py
ezsam/cli/formats.py
ezsam/cli/models.py
ezsam/cli/process.py
ezsam/gui/__init__.py
ezsam/gui/app.py
ezsam/gui/assets/README.md
ezsam/gui/assets/theme.json
ezsam/gui/config.py
ezsam/gui/models.py
ezsam/lib/config.py
ezsam/lib/date.py
ezsam/lib/downloader.py
ezsam/lib/file.py
ezsam/lib/gpu.py
ezsam/lib/logger.py
ezsam/lib/path.py
ezsam/lib/preview.py
ezsam/lib/resize.py
ezsam/lib/tkutils.py
ezsam-0.5.0.dist-info/RECORD
